<?xml version="1.0" encoding="utf-8"?>
<clothing-items>
 <clothing>
  <id>
   208810721
  </id>
  <name>
   Addidas Sweater I-1183
  </name>
  <category>
   Sweater
  </category>
  <size>
   S
  </size>
  <color>
   Оранжевый
  </color>
  <material>
   Нейлон
  </material>
  <price>
   637260
  </price>
  <rating>
   2.64
  </rating>
  <reviews>
   794528
  </reviews>
  <new>
   -
  </new>
  <exclusive>
   yes
  </exclusive>
 </clothing>
 <clothing>
  <id>
   887143665
  </id>
  <name>
   Reebok Skirt Z-9894
  </name>
  <category>
   Skirt
  </category>
  <size>
   M
  </size>
  <color>
   Зеленый
  </color>
  <material>
   Вискоза
  </material>
  <price>
   837852
  </price>
  <rating>
   3.97
  </rating>
  <reviews>
   208956
  </reviews>
  <new>
   -
  </new>
  <exclusive>
   yes
  </exclusive>
  <sporty>
   no
  </sporty>
 </clothing>
 <clothing>
  <id>
   988408765
  </id>
  <name>
   Converse Gloves I-1253
  </name>
  <category>
   Gloves
  </category>
  <size>
   M
  </size>
  <color>
   Голубой
  </color>
  <material>
   Шерсть
  </material>
  <price>
   471572
  </price>
  <rating>
   1.0
  </rating>
  <reviews>
   759529
  </reviews>
  <new>
   -
  </new>
  <exclusive>
   yes
  </exclusive>
  <sporty>
   yes
  </sporty>
 </clothing>
 <clothing>
  <id>
   800043586
  </id>
  <name>
   Lacoste Belts R-2602
  </name>
  <category>
   Belts
  </category>
  <size>
   M
  </size>
  <color>
   Голубой
  </color>
  <material>
   Вискоза
  </material>
  <price>
   490023
  </price>
  <rating>
   1.69
  </rating>
  <reviews>
   453911
  </reviews>
 </clothing>
 <clothing>
  <id>
   891115606
  </id>
  <name>
   Ellesse Shoes P-2348
  </name>
  <category>
   Shoes
  </category>
  <size>
   XXL
  </size>
  <color>
   Зеленый
  </color>
  <material>
   Лен
  </material>
  <price>
   433360
  </price>
  <rating>
   1.37
  </rating>
  <reviews>
   310706
  </reviews>
  <new>
   -
  </new>
  <exclusive>
   no
  </exclusive>
 </clothing>
 <clothing>
  <id>
   600439584
  </id>
  <name>
   Addidas Pants G-8587
  </name>
  <category>
   Pants
  </category>
  <size>
   XL
  </size>
  <color>
   Желтый
  </color>
  <material>
   Полиэстер
  </material>
  <price>
   109391
  </price>
  <rating>
   1.41
  </rating>
  <reviews>
   804619
  </reviews>
  <new>
   -
  </new>
  <exclusive>
   no
  </exclusive>
  <sporty>
   yes
  </sporty>
 </clothing>
 <clothing>
  <id>
   238895841
  </id>
  <name>
   Lacoste Hat Y-2806
  </name>
  <category>
   Hat
  </category>
  <size>
   L
  </size>
  <color>
   Зеленый
  </color>
  <material>
   Лен
  </material>
  <price>
   307299
  </price>
  <rating>
   1.33
  </rating>
  <reviews>
   477793
  </reviews>
  <new>
   +
  </new>
 </clothing>
 <clothing>
  <id>
   915425948
  </id>
  <name>
   Ellesse Shirt E-5510
  </name>
  <category>
   Shirt
  </category>
  <size>
   S
  </size>
  <color>
   Фиолетовый
  </color>
  <material>
   Вискоза
  </material>
  <price>
   146120
  </price>
  <rating>
   4.58
  </rating>
  <reviews>
   240476
  </reviews>
  <new>
   -
  </new>
  <exclusive>
   yes
  </exclusive>
 </clothing>
 <clothing>
  <id>
   290885992
  </id>
  <name>
   Fila Shirt R-2957
  </name>
  <category>
   Shirt
  </category>
  <size>
   XL
  </size>
  <color>
   Синий
  </color>
  <material>
   Шерсть
  </material>
  <price>
   377668
  </price>
  <rating>
   4.22
  </rating>
  <reviews>
   503588
  </reviews>
  <exclusive>
   no
  </exclusive>
  <sporty>
   yes
  </sporty>
 </clothing>
 <clothing>
  <id>
   404940860
  </id>
  <name>
   Fila Socks U-3959
  </name>
  <category>
   Socks
  </category>
  <size>
   L
  </size>
  <color>
   Красный
  </color>
  <material>
   Шелк
  </material>
  <price>
   901603
  </price>
  <rating>
   3.79
  </rating>
  <reviews>
   7318
  </reviews>
  <sporty>
   yes
  </sporty>
 </clothing>
 <clothing>
  <id>
   606812946
  </id>
  <name>
   New Balance Gloves X-2649
  </name>
  <category>
   Gloves
  </category>
  <size>
   XXL
  </size>
  <color>
   Красный
  </color>
  <material>
   Хлопок
  </material>
  <price>
   296521
  </price>
  <rating>
   3.42
  </rating>
  <reviews>
   762773
  </reviews>
  <new>
   -
  </new>
  <sporty>
   no
  </sporty>
 </clothing>
 <clothing>
  <id>
   749676497
  </id>
  <name>
   Ellesse Jacket D-4909
  </name>
  <category>
   Jacket
  </category>
  <size>
   XL
  </size>
  <color>
   Желтый
  </color>
  <material>
   Шерсть
  </material>
  <price>
   728466
  </price>
  <rating>
   3.94
  </rating>
  <reviews>
   157262
  </reviews>
  <new>
   -
  </new>
  <exclusive>
   yes
  </exclusive>
 </clothing>
 <clothing>
  <id>
   627953668
  </id>
  <name>
   Vans Shoes N-3103
  </name>
  <category>
   Shoes
  </category>
  <size>
   XXL
  </size>
  <color>
   Голубой
  </color>
  <material>
   Лен
  </material>
  <price>
   933787
  </price>
  <rating>
   3.98
  </rating>
  <reviews>
   694566
  </reviews>
  <exclusive>
   no
  </exclusive>
 </clothing>
 <clothing>
  <id>
   205812265
  </id>
  <name>
   Ellesse Skirt K-6765
  </name>
  <category>
   Skirt
  </category>
  <size>
   L
  </size>
  <color>
   Зеленый
  </color>
  <material>
   Лен
  </material>
  <price>
   401851
  </price>
  <rating>
   2.64
  </rating>
  <reviews>
   72862
  </reviews>
  <new>
   -
  </new>
  <exclusive>
   yes
  </exclusive>
  <sporty>
   yes
  </sporty>
 </clothing>
 <clothing>
  <id>
   886644217
  </id>
  <name>
   Puma Jeans R-1717
  </name>
  <category>
   Jeans
  </category>
  <size>
   S
  </size>
  <color>
   Синий
  </color>
  <material>
   Кожа
  </material>
  <price>
   236773
  </price>
  <rating>
   3.27
  </rating>
  <reviews>
   662159
  </reviews>
  <exclusive>
   no
  </exclusive>
  <sporty>
   no
  </sporty>
 </clothing>
 <clothing>
  <id>
   169715622
  </id>
  <name>
   Brooks Dress X-8725
  </name>
  <category>
   Dress
  </category>
  <size>
   L
  </size>
  <color>
   Фиолетовый
  </color>
  <material>
   Хлопок
  </material>
  <price>
   679779
  </price>
  <rating>
   2.03
  </rating>
  <reviews>
   109809
  </reviews>
  <new>
   -
  </new>
  <sporty>
   yes
  </sporty>
 </clothing>
 <clothing>
  <id>
   988345075
  </id>
  <name>
   Fila Socks S-2816
  </name>
  <category>
   Socks
  </category>
  <size>
   XL
  </size>
  <color>
   Синий
  </color>
  <material>
   Полиэстер
  </material>
  <price>
   961781
  </price>
  <rating>
   2.67
  </rating>
  <reviews>
   949251
  </reviews>
  <new>
   +
  </new>
  <sporty>
   yes
  </sporty>
 </clothing>
 <clothing>
  <id>
   818549475
  </id>
  <name>
   New Balance Hat Z-8723
  </name>
  <category>
   Hat
  </category>
  <size>
   M
  </size>
  <color>
   Желтый
  </color>
  <material>
   Лен
  </material>
  <price>
   533426
  </price>
  <rating>
   2.43
  </rating>
  <reviews>
   17924
  </reviews>
  <new>
   -
  </new>
  <exclusive>
   no
  </exclusive>
 </clothing>
 <clothing>
  <id>
   758996862
  </id>
  <name>
   PleinSport Blouse H-5964
  </name>
  <category>
   Blouse
  </category>
  <size>
   XXL
  </size>
  <color>
   Зеленый
  </color>
  <material>
   Вискоза
  </material>
  <price>
   546012
  </price>
  <rating>
   3.86
  </rating>
  <reviews>
   329866
  </reviews>
  <new>
   -
  </new>
  <exclusive>
   no
  </exclusive>
  <sporty>
   yes
  </sporty>
 </clothing>
 <clothing>
  <id>
   962284096
  </id>
  <name>
   Fila Skirt K-6427
  </name>
  <category>
   Skirt
  </category>
  <size>
   L
  </size>
  <color>
   Красный
  </color>
  <material>
   Нейлон
  </material>
  <price>
   192180
  </price>
  <rating>
   4.79
  </rating>
  <reviews>
   120159
  </reviews>
  <sporty>
   no
  </sporty>
 </clothing>
 <clothing>
  <id>
   605794803
  </id>
  <name>
   Asics Socks M-8798
  </name>
  <category>
   Socks
  </category>
  <size>
   L
  </size>
  <color>
   Зеленый
  </color>
  <material>
   Хлопок
  </material>
  <price>
   576485
  </price>
  <rating>
   1.38
  </rating>
  <reviews>
   738596
  </reviews>
  <exclusive>
   no
  </exclusive>
 </clothing>
 <clothing>
  <id>
   879485964
  </id>
  <name>
   Puma Dress I-8079
  </name>
  <category>
   Dress
  </category>
  <size>
   S
  </size>
  <color>
   Оранжевый
  </color>
  <material>
   Кожа
  </material>
  <price>
   763080
  </price>
  <rating>
   4.73
  </rating>
  <reviews>
   493641
  </reviews>
  <new>
   +
  </new>
  <exclusive>
   yes
  </exclusive>
  <sporty>
   no
  </sporty>
 </clothing>
 <clothing>
  <id>
   312700961
  </id>
  <name>
   Puma Handbags G-6332
  </name>
  <category>
   Handbags
  </category>
  <size>
   M
  </size>
  <color>
   Синий
  </color>
  <material>
   Хлопок
  </material>
  <price>
   724306
  </price>
  <rating>
   3.54
  </rating>
  <reviews>
   132428
  </reviews>
  <sporty>
   yes
  </sporty>
 </clothing>
 <clothing>
  <id>
   960920757
  </id>
  <name>
   Converse Jacket X-1614
  </name>
  <category>
   Jacket
  </category>
  <size>
   XXL
  </size>
  <color>
   Желтый
  </color>
  <material>
   Кожа
  </material>
  <price>
   454600
  </price>
  <rating>
   4.29
  </rating>
  <reviews>
   594932
  </reviews>
  <new>
   -
  </new>
  <sporty>
   yes
  </sporty>
 </clothing>
 <clothing>
  <id>
   117145171
  </id>
  <name>
   New Balance Shirt Y-8437
  </name>
  <category>
   Shirt
  </category>
  <size>
   S
  </size>
  <color>
   Фиолетовый
  </color>
  <material>
   Шерсть
  </material>
  <price>
   131322
  </price>
  <rating>
   2.33
  </rating>
  <reviews>
   325989
  </reviews>
  <sporty>
   no
  </sporty>
 </clothing>
 <clothing>
  <id>
   710149582
  </id>
  <name>
   Adidas Shoes U-8247
  </name>
  <category>
   Shoes
  </category>
  <size>
   M
  </size>
  <color>
   Фиолетовый
  </color>
  <material>
   Лен
  </material>
  <price>
   236511
  </price>
  <rating>
   2.35
  </rating>
  <reviews>
   396196
  </reviews>
 </clothing>
 <clothing>
  <id>
   446569981
  </id>
  <name>
   Under Armour T-shirt M-9386
  </name>
  <category>
   T-shirt
  </category>
  <size>
   S
  </size>
  <color>
   Голубой
  </color>
  <material>
   Нейлон
  </material>
  <price>
   448204
  </price>
  <rating>
   4.61
  </rating>
  <reviews>
   797167
  </reviews>
  <sporty>
   yes
  </sporty>
 </clothing>
 <clothing>
  <id>
   133780729
  </id>
  <name>
   DC Blouse K-2957
  </name>
  <category>
   Blouse
  </category>
  <size>
   XL
  </size>
  <color>
   Желтый
  </color>
  <material>
   Кожа
  </material>
  <price>
   448848
  </price>
  <rating>
   4.73
  </rating>
  <reviews>
   816834
  </reviews>
  <new>
   -
  </new>
  <exclusive>
   no
  </exclusive>
  <sporty>
   no
  </sporty>
 </clothing>
 <clothing>
  <id>
   730565160
  </id>
  <name>
   Lacoste Jacket J-5572
  </name>
  <category>
   Jacket
  </category>
  <size>
   L
  </size>
  <color>
   Красный
  </color>
  <material>
   Полиэстер
  </material>
  <price>
   190724
  </price>
  <rating>
   3.66
  </rating>
  <reviews>
   43507
  </reviews>
  <new>
   -
  </new>
 </clothing>
 <clothing>
  <id>
   897668255
  </id>
  <name>
   Puma Blouse B-3801
  </name>
  <category>
   Blouse
  </category>
  <size>
   S
  </size>
  <color>
   Фиолетовый
  </color>
  <material>
   Шелк
  </material>
  <price>
   262097
  </price>
  <rating>
   5.0
  </rating>
  <reviews>
   887096
  </reviews>
  <new>
   -
  </new>
 </clothing>
 <clothing>
  <id>
   938741424
  </id>
  <name>
   Brooks Shoes V-8270
  </name>
  <category>
   Shoes
  </category>
  <size>
   L
  </size>
  <color>
   Синий
  </color>
  <material>
   Нейлон
  </material>
  <price>
   848343
  </price>
  <rating>
   1.05
  </rating>
  <reviews>
   574997
  </reviews>
 </clothing>
 <clothing>
  <id>
   571102740
  </id>
  <name>
   Reebok Jacket T-6808
  </name>
  <category>
   Jacket
  </category>
  <size>
   S
  </size>
  <color>
   Синий
  </color>
  <material>
   Нейлон
  </material>
  <price>
   278189
  </price>
  <rating>
   3.64
  </rating>
  <reviews>
   321460
  </reviews>
  <sporty>
   no
  </sporty>
 </clothing>
 <clothing>
  <id>
   600056497
  </id>
  <name>
   Converse Umbrellas G-7574
  </name>
  <category>
   Umbrellas
  </category>
  <size>
   M
  </size>
  <color>
   Зеленый
  </color>
  <material>
   Полиэстер
  </material>
  <price>
   549274
  </price>
  <rating>
   3.9
  </rating>
  <reviews>
   561148
  </reviews>
  <new>
   -
  </new>
  <exclusive>
   no
  </exclusive>
 </clothing>
 <clothing>
  <id>
   123851070
  </id>
  <name>
   Ellesse T-shirt P-9642
  </name>
  <category>
   T-shirt
  </category>
  <size>
   XL
  </size>
  <color>
   Голубой
  </color>
  <material>
   Шерсть
  </material>
  <price>
   331803
  </price>
  <rating>
   4.84
  </rating>
  <reviews>
   952392
  </reviews>
  <new>
   +
  </new>
  <exclusive>
   no
  </exclusive>
 </clothing>
 <clothing>
  <id>
   663629406
  </id>
  <name>
   Converse Shirt I-8731
  </name>
  <category>
   Shirt
  </category>
  <size>
   L
  </size>
  <color>
   Зеленый
  </color>
  <material>
   Кожа
  </material>
  <price>
   839779
  </price>
  <rating>
   3.25
  </rating>
  <reviews>
   592424
  </reviews>
  <new>
   +
  </new>
  <sporty>
   no
  </sporty>
 </clothing>
 <clothing>
  <id>
   431709058
  </id>
  <name>
   Adidas Sweater U-7207
  </name>
  <category>
   Sweater
  </category>
  <size>
   S
  </size>
  <color>
   Синий
  </color>
  <material>
   Шелк
  </material>
  <price>
   420964
  </price>
  <rating>
   1.61
  </rating>
  <reviews>
   846840
  </reviews>
  <exclusive>
   no
  </exclusive>
  <sporty>
   yes
  </sporty>
 </clothing>
 <clothing>
  <id>
   924405097
  </id>
  <name>
   New Balance Sweater H-8724
  </name>
  <category>
   Sweater
  </category>
  <size>
   L
  </size>
  <color>
   Зеленый
  </color>
  <material>
   Кожа
  </material>
  <price>
   830370
  </price>
  <rating>
   4.72
  </rating>
  <reviews>
   966798
  </reviews>
  <new>
   +
  </new>
  <sporty>
   no
  </sporty>
 </clothing>
 <clothing>
  <id>
   180828804
  </id>
  <name>
   Adidas Jeans Q-2770
  </name>
  <category>
   Jeans
  </category>
  <size>
   M
  </size>
  <color>
   Синий
  </color>
  <material>
   Вискоза
  </material>
  <price>
   556590
  </price>
  <rating>
   1.1
  </rating>
  <reviews>
   440740
  </reviews>
  <exclusive>
   no
  </exclusive>
  <sporty>
   no
  </sporty>
 </clothing>
 <clothing>
  <id>
   894387695
  </id>
  <name>
   Converse Blouse V-2850
  </name>
  <category>
   Blouse
  </category>
  <size>
   M
  </size>
  <color>
   Фиолетовый
  </color>
  <material>
   Вискоза
  </material>
  <price>
   752225
  </price>
  <rating>
   2.07
  </rating>
  <reviews>
   508716
  </reviews>
  <new>
   -
  </new>
  <sporty>
   yes
  </sporty>
 </clothing>
 <clothing>
  <id>
   683386574
  </id>
  <name>
   Ellesse T-shirt I-2418
  </name>
  <category>
   T-shirt
  </category>
  <size>
   XL
  </size>
  <color>
   Синий
  </color>
  <material>
   Хлопок
  </material>
  <price>
   417298
  </price>
  <rating>
   1.34
  </rating>
  <reviews>
   84198
  </reviews>
  <new>
   +
  </new>
 </clothing>
 <clothing>
  <id>
   664677759
  </id>
  <name>
   DC Blouse W-2230
  </name>
  <category>
   Blouse
  </category>
  <size>
   S
  </size>
  <color>
   Красный
  </color>
  <material>
   Кожа
  </material>
  <price>
   565340
  </price>
  <rating>
   4.15
  </rating>
  <reviews>
   598138
  </reviews>
  <exclusive>
   no
  </exclusive>
  <sporty>
   no
  </sporty>
 </clothing>
 <clothing>
  <id>
   228174590
  </id>
  <name>
   Vans Dress U-6527
  </name>
  <category>
   Dress
  </category>
  <size>
   M
  </size>
  <color>
   Синий
  </color>
  <material>
   Шелк
  </material>
  <price>
   378918
  </price>
  <rating>
   2.32
  </rating>
  <reviews>
   519188
  </reviews>
  <exclusive>
   no
  </exclusive>
  <sporty>
   no
  </sporty>
 </clothing>
 <clothing>
  <id>
   747193687
  </id>
  <name>
   DC Pants E-7485
  </name>
  <category>
   Pants
  </category>
  <size>
   M
  </size>
  <color>
   Красный
  </color>
  <material>
   Полиэстер
  </material>
  <price>
   393539
  </price>
  <rating>
   2.82
  </rating>
  <reviews>
   389501
  </reviews>
  <new>
   +
  </new>
 </clothing>
 <clothing>
  <id>
   184999222
  </id>
  <name>
   New Balance T-shirt Z-8205
  </name>
  <category>
   T-shirt
  </category>
  <size>
   M
  </size>
  <color>
   Оранжевый
  </color>
  <material>
   Полиэстер
  </material>
  <price>
   970063
  </price>
  <rating>
   4.12
  </rating>
  <reviews>
   778338
  </reviews>
  <new>
   -
  </new>
  <exclusive>
   yes
  </exclusive>
 </clothing>
</clothing-items>
